{"mc":{
	"r1_4r":{
		"frameRate":24,
		"labels":[
			{"name":"action","frame":6}
			
			],
		"frames":[
			
			{"res":"7DB7F4A7","x":-33,"y":-59},
{"res":"9FD01CC5","x":-34,"y":-62},
{"res":"406F6A58","x":-32,"y":-60},
{"res":"AB72D2BA","x":-31,"y":-58},
{"res":"5F39DCE","x":-30,"y":-63},
{"res":"3DCBEF03","x":-32,"y":-61}
			]
}},
	"res":{
		"7DB7F4A7":{"x":65,"y":1,"w":63,"h":88},
		"9FD01CC5":{"x":1,"y":101,"w":62,"h":97},
		"406F6A58":{"x":130,"y":90,"w":62,"h":86},
		"AB72D2BA":{"x":65,"y":91,"w":63,"h":87},
		"5F39DCE":{"x":1,"y":1,"w":62,"h":98},
		"3DCBEF03":{"x":130,"y":1,"w":63,"h":87}
	}}